MANIFEST.in
setup.py
jsonclient/__init__.py
jsonclient/__init__.pyc
jsonclient/client.py
jsonclient/client.pyc
jsonrpc_client.egg-info/PKG-INFO
jsonrpc_client.egg-info/SOURCES.txt
jsonrpc_client.egg-info/dependency_links.txt
jsonrpc_client.egg-info/requires.txt
jsonrpc_client.egg-info/top_level.txt