Metadata-Version: 1.0
Name: jsonrpc-client
Version: 0.1.1
Summary: Another python json-rpc client
Home-page: https://github.com/lerry/jsonrpc-client
Author: Lerry
Author-email: lvdachao@gmail.com
License: MIT
Platform: any
